pgworkload/__init__.py
pgworkload/cli/dep.py
pgworkload/cli/main.py
pgworkload/cli/util.py
pgworkload/models/init.py
pgworkload/models/run.py
pgworkload/models/util.py
pgworkload/utils/builtin_workloads.py
pgworkload/utils/common.py
pgworkload/utils/simplefaker.py
pgworkload-0.1.12.dist-info/LICENSE
pgworkload-0.1.12.dist-info/METADATA
pgworkload-0.1.12.dist-info/WHEEL
pgworkload-0.1.12.dist-info/entry_points.txt
pgworkload-0.1.12.dist-info/RECORD
